<process name="Smalltalk Dolphin Button Process" version="1.0" narrative="." preferredid="727638a8-551a-4ad0-b756-c00eb5ed8b96">
  <view>
    <camerax>0</camerax>
    <cameray>0</cameray>
    <zoom>1</zoom>
  </view>
  <preconditions />
  <endpoint narrative="" />
  <stage stageid="0d21d3cb-31fb-40f8-8dcc-620291ecdd8c" name="Stage1" type="ProcessInfo">
    <narrative>
    </narrative>
    <displayx>-195</displayx>
    <displayy>-105</displayy>
    <displaywidth>150</displaywidth>
    <displayheight>90</displayheight>
    <font family="Tahoma" size="10" style="Regular" color="000000" />
  </stage>
  <stage stageid="150197e1-eb55-40e7-9860-6ad6a3ec1f63" name="Start" type="Start">
    <narrative>
    </narrative>
    <displayx>90</displayx>
    <displayy>-105</displayy>
    <displaywidth>60</displaywidth>
    <displayheight>30</displayheight>
    <font family="Tahoma" size="10" style="Regular" color="000000" />
    <action />
    <inputs />
    <outputs />
    <onsuccess>cd350ac4-48ec-42fd-a34e-3d4832bce5ec</onsuccess>
  </stage>
  <stage stageid="0920dc49-7fbd-441e-8ba0-c554bc71dbed" name="press button" type="Action">
    <narrative>
    </narrative>
    <displayx>180</displayx>
    <displayy>0</displayy>
    <displaywidth>60</displaywidth>
    <displayheight>30</displayheight>
    <font family="Tahoma" size="10" style="Regular" color="000000" />
    <action />
    <inputs>
      <input type="flag" name="Use AA" expr="[Use AA]" />
    </inputs>
    <outputs>
      <output type="flag" name="Success" stage="Button Pressed" />
    </outputs>
    <onsuccess>4101c95d-f1cc-4936-aeb1-7340e2002c6a</onsuccess>
    <resource object="Smalltalk Dolphin" action="Press button" />
  </stage>
  <stage stageid="cc4ed6f7-296e-4b3a-b29f-ee35016e848f" name="Use Win32" type="Calculation">
    <narrative>
    </narrative>
    <displayx>90</displayx>
    <displayy>0</displayy>
    <displaywidth>60</displaywidth>
    <displayheight>30</displayheight>
    <font family="Tahoma" size="10" style="Regular" color="000000" />
    <onsuccess>0920dc49-7fbd-441e-8ba0-c554bc71dbed</onsuccess>
    <calculation expression="False" stage="Use AA" />
  </stage>
  <stage stageid="93536a76-6b46-4f4a-bdc2-65e7b2bc6d22" name="press button" type="Action">
    <narrative>
    </narrative>
    <displayx>180</displayx>
    <displayy>210</displayy>
    <displaywidth>60</displaywidth>
    <displayheight>30</displayheight>
    <font family="Tahoma" size="10" style="Regular" color="000000" />
    <action />
    <inputs>
      <input type="flag" name="Use AA" expr="[Use AA]" />
    </inputs>
    <outputs>
      <output type="flag" name="Success" stage="Button Pressed" />
    </outputs>
    <onsuccess>4124f48e-5879-4ff0-9bb1-ede552abc499</onsuccess>
    <resource object="Smalltalk Dolphin" action="Press button" />
  </stage>
  <stage stageid="61306768-beed-4349-88e2-eadd5b6219f8" name="Use AA" type="Calculation">
    <narrative>
    </narrative>
    <displayx>90</displayx>
    <displayy>210</displayy>
    <displaywidth>60</displaywidth>
    <displayheight>30</displayheight>
    <font family="Tahoma" size="10" style="Regular" color="000000" />
    <onsuccess>93536a76-6b46-4f4a-bdc2-65e7b2bc6d22</onsuccess>
    <calculation expression="True" stage="Use AA" />
  </stage>
  <stage stageid="790e7a06-73ce-43a6-bba3-428d03d22517" name="Button Pressed" type="Data">
    <narrative>
    </narrative>
    <displayx>-60</displayx>
    <displayy>15</displayy>
    <displaywidth>120</displaywidth>
    <displayheight>30</displayheight>
    <font family="Tahoma" size="10" style="Regular" color="000000" />
    <datatype>flag</datatype>
    <initialvalue>False</initialvalue>
    <private />
    <alwaysinit />
  </stage>
  <stage stageid="4101c95d-f1cc-4936-aeb1-7340e2002c6a" name="Pressed?" type="Decision">
    <narrative>
    </narrative>
    <displayx>270</displayx>
    <displayy>0</displayy>
    <displaywidth>60</displaywidth>
    <displayheight>30</displayheight>
    <font family="Tahoma" size="10" style="Regular" color="000000" />
    <decision expression="[Button Pressed]" />
    <ontrue>e2e1c5a1-73b1-4ee3-ac6c-c132a64a63ed</ontrue>
    <onfalse>ee97904e-c5c5-49a1-80dd-49a585c1eee8</onfalse>
  </stage>
  <stage stageid="4124f48e-5879-4ff0-9bb1-ede552abc499" name="Pressed?" type="Decision">
    <narrative>
    </narrative>
    <displayx>270</displayx>
    <displayy>210</displayy>
    <displaywidth>60</displaywidth>
    <displayheight>30</displayheight>
    <font family="Tahoma" size="10" style="Regular" color="000000" />
    <decision expression="[Button Pressed]" />
    <ontrue>6a316425-fdfd-4422-a4bc-a4d102c093be</ontrue>
    <onfalse>9f24745b-9879-46cb-904e-15d8a626efea</onfalse>
  </stage>
  <stage stageid="ee97904e-c5c5-49a1-80dd-49a585c1eee8" name="Note1" type="Note">
    <narrative>win32 button press failed</narrative>
    <displayx>270</displayx>
    <displayy>-60</displayy>
    <displaywidth>90</displaywidth>
    <displayheight>30</displayheight>
    <font family="Tahoma" size="10" style="Regular" color="000000" />
    <onsuccess>da556947-5498-4b00-9f3f-ad3e93fbecc4</onsuccess>
  </stage>
  <stage stageid="9f24745b-9879-46cb-904e-15d8a626efea" name="Note1" type="Note">
    <narrative>AA button press failed</narrative>
    <displayx>270</displayx>
    <displayy>150</displayy>
    <displaywidth>90</displaywidth>
    <displayheight>30</displayheight>
    <font family="Tahoma" size="10" style="Regular" color="000000" />
    <onsuccess>249e72da-14e0-48de-9bee-522aae0384cc</onsuccess>
  </stage>
  <stage stageid="da556947-5498-4b00-9f3f-ad3e93fbecc4" name="anchor13" type="Anchor">
    <narrative>
    </narrative>
    <displayx>270</displayx>
    <displayy>-105</displayy>
    <displaywidth>10</displaywidth>
    <displayheight>10</displayheight>
    <font family="Tahoma" size="10" style="Regular" color="000000" />
    <onsuccess>f37a6324-022e-4313-aef3-af189d327828</onsuccess>
  </stage>
  <stage stageid="249e72da-14e0-48de-9bee-522aae0384cc" name="anchor14" type="Anchor">
    <narrative>
    </narrative>
    <displayx>270</displayx>
    <displayy>105</displayy>
    <displaywidth>10</displaywidth>
    <displayheight>10</displayheight>
    <font family="Tahoma" size="10" style="Regular" color="000000" />
    <onsuccess>98400aff-5ae7-4226-bdb4-6b53a385ea67</onsuccess>
  </stage>
  <stage stageid="4fdf3ba3-2d6c-48ae-86c7-908103711206" name="terminate" type="Action">
    <narrative>
    </narrative>
    <displayx>540</displayx>
    <displayy>210</displayy>
    <displaywidth>60</displaywidth>
    <displayheight>30</displayheight>
    <font family="Tahoma" size="10" style="Regular" color="000000" />
    <action />
    <inputs />
    <outputs />
    <onsuccess>631c0ec2-adbf-43a0-b7c3-8ade312c2225</onsuccess>
    <resource object="Smalltalk Dolphin" action="Terminate" />
  </stage>
  <stage stageid="631c0ec2-adbf-43a0-b7c3-8ade312c2225" name="End2" type="End">
    <narrative>
    </narrative>
    <displayx>630</displayx>
    <displayy>210</displayy>
    <displaywidth>60</displaywidth>
    <displayheight>30</displayheight>
    <font family="Tahoma" size="10" style="Regular" color="000000" />
    <action />
    <inputs />
    <outputs />
  </stage>
  <stage stageid="cd350ac4-48ec-42fd-a34e-3d4832bce5ec" name="launch" type="Action">
    <narrative>
    </narrative>
    <displayx>90</displayx>
    <displayy>-60</displayy>
    <displaywidth>60</displaywidth>
    <displayheight>30</displayheight>
    <font family="Tahoma" size="10" style="Regular" color="000000" />
    <action />
    <inputs />
    <outputs />
    <onsuccess>cc4ed6f7-296e-4b3a-b29f-ee35016e848f</onsuccess>
    <resource object="Smalltalk Dolphin" action="Launch" />
  </stage>
  <stage stageid="22962834-f88d-4e31-bd66-11212fefe0a9" name="Use AA" type="Data">
    <narrative>
    </narrative>
    <displayx>-60</displayx>
    <displayy>60</displayy>
    <displaywidth>120</displaywidth>
    <displayheight>30</displayheight>
    <font family="Tahoma" size="10" style="Regular" color="000000" />
    <datatype>flag</datatype>
    <initialvalue>False</initialvalue>
    <private />
    <alwaysinit />
  </stage>
  <stage stageid="b1d97c3b-ce4b-42c4-9d89-1660e7fc8036" name="anchor8" type="Anchor">
    <narrative>
    </narrative>
    <displayx>450</displayx>
    <displayy>60</displayy>
    <displaywidth>10</displaywidth>
    <displayheight>10</displayheight>
    <font family="Tahoma" size="10" style="Regular" color="000000" />
    <onsuccess>816ac8b0-de64-4ae5-b649-6ee5d47d0ed6</onsuccess>
  </stage>
  <stage stageid="816ac8b0-de64-4ae5-b649-6ee5d47d0ed6" name="anchor10" type="Anchor">
    <narrative>
    </narrative>
    <displayx>90</displayx>
    <displayy>60</displayy>
    <displaywidth>10</displaywidth>
    <displayheight>10</displayheight>
    <font family="Tahoma" size="10" style="Regular" color="000000" />
    <onsuccess>61306768-beed-4349-88e2-eadd5b6219f8</onsuccess>
  </stage>
  <stage stageid="e2e1c5a1-73b1-4ee3-ac6c-c132a64a63ed" name="get text" type="Action">
    <narrative>
    </narrative>
    <displayx>360</displayx>
    <displayy>0</displayy>
    <displaywidth>60</displaywidth>
    <displayheight>30</displayheight>
    <font family="Tahoma" size="10" style="Regular" color="000000" />
    <action />
    <inputs>
      <input type="flag" name="Use AA" expr="[Use AA]" />
    </inputs>
    <outputs>
      <output type="text" name="Text" stage="button text" />
    </outputs>
    <onsuccess>f7c1e3f9-7e5e-42e9-9476-402177680548</onsuccess>
    <resource object="Smalltalk Dolphin" action="Get Button Text" />
  </stage>
  <stage stageid="f7c1e3f9-7e5e-42e9-9476-402177680548" name="got text?" type="Decision">
    <narrative>
    </narrative>
    <displayx>450</displayx>
    <displayy>0</displayy>
    <displaywidth>60</displaywidth>
    <displayheight>30</displayheight>
    <font family="Tahoma" size="10" style="Regular" color="000000" />
    <decision expression="[button text]=&quot;Folder&quot;" />
    <ontrue>b1d97c3b-ce4b-42c4-9d89-1660e7fc8036</ontrue>
    <onfalse>0cf47ca5-7d21-4b50-bd55-aaae3c549d37</onfalse>
  </stage>
  <stage stageid="0cf47ca5-7d21-4b50-bd55-aaae3c549d37" name="Note4" type="Note">
    <narrative>win32 failed to get button text</narrative>
    <displayx>450</displayx>
    <displayy>-60</displayy>
    <displaywidth>60</displaywidth>
    <displayheight>30</displayheight>
    <font family="Tahoma" size="10" style="Regular" color="000000" />
    <onsuccess>f37a6324-022e-4313-aef3-af189d327828</onsuccess>
  </stage>
  <stage stageid="f37a6324-022e-4313-aef3-af189d327828" name="anchor30" type="Anchor">
    <narrative>
    </narrative>
    <displayx>450</displayx>
    <displayy>-105</displayy>
    <displaywidth>10</displaywidth>
    <displayheight>10</displayheight>
    <font family="Tahoma" size="10" style="Regular" color="000000" />
    <onsuccess>24444996-1046-4997-b876-eda6963899ae</onsuccess>
  </stage>
  <stage stageid="27d194e3-067c-4896-9e71-2f9f538e131e" name="got text?" type="Decision">
    <narrative>
    </narrative>
    <displayx>450</displayx>
    <displayy>210</displayy>
    <displaywidth>60</displaywidth>
    <displayheight>30</displayheight>
    <font family="Tahoma" size="10" style="Regular" color="000000" />
    <decision expression="[button text]=&quot;Folder&quot;" />
    <ontrue>4fdf3ba3-2d6c-48ae-86c7-908103711206</ontrue>
    <onfalse>637e467b-07d1-492e-86b3-1fb734a815cb</onfalse>
  </stage>
  <stage stageid="637e467b-07d1-492e-86b3-1fb734a815cb" name="Note4" type="Note">
    <narrative>AA failed to get button text</narrative>
    <displayx>450</displayx>
    <displayy>150</displayy>
    <displaywidth>60</displaywidth>
    <displayheight>30</displayheight>
    <font family="Tahoma" size="10" style="Regular" color="000000" />
    <onsuccess>98400aff-5ae7-4226-bdb4-6b53a385ea67</onsuccess>
  </stage>
  <stage stageid="98400aff-5ae7-4226-bdb4-6b53a385ea67" name="anchor30" type="Anchor">
    <narrative>
    </narrative>
    <displayx>450</displayx>
    <displayy>105</displayy>
    <displaywidth>10</displaywidth>
    <displayheight>10</displayheight>
    <font family="Tahoma" size="10" style="Regular" color="000000" />
    <onsuccess>48b27387-858f-441c-abe9-0e48a6e02db0</onsuccess>
  </stage>
  <stage stageid="6a316425-fdfd-4422-a4bc-a4d102c093be" name="get text" type="Action">
    <narrative>
    </narrative>
    <displayx>360</displayx>
    <displayy>210</displayy>
    <displaywidth>60</displaywidth>
    <displayheight>30</displayheight>
    <font family="Tahoma" size="10" style="Regular" color="000000" />
    <action />
    <inputs>
      <input type="flag" name="Use AA" expr="[Use AA]" />
    </inputs>
    <outputs>
      <output type="text" name="Text" stage="button text" />
    </outputs>
    <onsuccess>27d194e3-067c-4896-9e71-2f9f538e131e</onsuccess>
    <resource object="Smalltalk Dolphin" action="Get Button Text" />
  </stage>
  <stage stageid="48b27387-858f-441c-abe9-0e48a6e02db0" name="terminate" type="Action">
    <narrative>
    </narrative>
    <displayx>540</displayx>
    <displayy>105</displayy>
    <displaywidth>60</displaywidth>
    <displayheight>30</displayheight>
    <font family="Tahoma" size="10" style="Regular" color="000000" />
    <action />
    <inputs />
    <outputs />
    <resource object="Smalltalk Dolphin" action="Terminate" />
  </stage>
  <stage stageid="24444996-1046-4997-b876-eda6963899ae" name="terminate" type="Action">
    <narrative>
    </narrative>
    <displayx>540</displayx>
    <displayy>-105</displayy>
    <displaywidth>60</displaywidth>
    <displayheight>30</displayheight>
    <font family="Tahoma" size="10" style="Regular" color="000000" />
    <action />
    <inputs />
    <outputs />
    <resource object="Smalltalk Dolphin" action="Terminate" />
  </stage>
  <stage stageid="3e9c2a2e-0421-4cc6-9704-e4e108f61a7b" name="button text" type="Data">
    <narrative>
    </narrative>
    <displayx>-60</displayx>
    <displayy>105</displayy>
    <displaywidth>120</displaywidth>
    <displayheight>30</displayheight>
    <font family="Tahoma" size="10" style="Regular" color="000000" />
    <datatype>text</datatype>
    <initialvalue>
    </initialvalue>
    <private />
    <alwaysinit />
  </stage>
</process>